MANIFEST.in
README.txt
setup.cfg
setup.py
docs/HISTORY.txt
docs/INSTALL.txt
docs/LICENSE.GPL
docs/LICENSE.txt
enpraxis/__init__.py
enpraxis.educommons.egg-info/PKG-INFO
enpraxis.educommons.egg-info/SOURCES.txt
enpraxis.educommons.egg-info/dependency_links.txt
enpraxis.educommons.egg-info/entry_points.txt
enpraxis.educommons.egg-info/namespace_packages.txt
enpraxis.educommons.egg-info/not-zip-safe
enpraxis.educommons.egg-info/requires.txt
enpraxis.educommons.egg-info/top_level.txt
enpraxis/educommons/CHANGES.txt
enpraxis/educommons/IMSContentPackaging.txt
enpraxis/educommons/INSTALL.txt
enpraxis/educommons/LOCALIZATION.txt
enpraxis/educommons/MIGRATION.txt
enpraxis/educommons/MIGRATIONS_OLD.txt
enpraxis/educommons/PORTLETS.txt
enpraxis/educommons/SETUP.txt
enpraxis/educommons/SeleniumRCTests.txt
enpraxis/educommons/__init__.py
enpraxis/educommons/__pkginfo__.py
enpraxis/educommons/config.py
enpraxis/educommons/configure.zcml
enpraxis/educommons/eventHandlers.py
enpraxis/educommons/events.py
enpraxis/educommons/interfaces.py
enpraxis/educommons/loadtesttool.py
enpraxis/educommons/overrides.zcml
enpraxis/educommons/setupHandlers.py
enpraxis/educommons/setupHandlersOpenOCW.py
enpraxis/educommons/tool.gif
enpraxis/educommons/version.txt
enpraxis/educommons/annotations/__init__.py
enpraxis/educommons/annotations/configure.zcml
enpraxis/educommons/annotations/fields.py
enpraxis/educommons/annotations/indexers.py
enpraxis/educommons/annotations/interfaces.py
enpraxis/educommons/browser/__init__.py
enpraxis/educommons/browser/accessibility_compliant.pt
enpraxis/educommons/browser/accessibilityview.py
enpraxis/educommons/browser/ada_compliant.pt
enpraxis/educommons/browser/adaview.py
enpraxis/educommons/browser/authors.pt
enpraxis/educommons/browser/authors.py
enpraxis/educommons/browser/cc_table.pt
enpraxis/educommons/browser/citation_view.pt
enpraxis/educommons/browser/clear_copyright.pt
enpraxis/educommons/browser/colophon.pt
enpraxis/educommons/browser/colophon.py
enpraxis/educommons/browser/configure.zcml
enpraxis/educommons/browser/controlpanel.py
enpraxis/educommons/browser/copyright_byline.pt
enpraxis/educommons/browser/copyrightview.py
enpraxis/educommons/browser/coursenavposition.py
enpraxis/educommons/browser/courseslisting.pt
enpraxis/educommons/browser/courseslisting.py
