Metadata-Version: 1.1
Name: enpraxis.educommons
Version: 4.1.2
Summary: A content management system for OpenCourseWare and OER rrelated materials.
Home-page: http://educommons.com
Author: enPraxis
Author-email: developer@enpraxis.net
License: GPL
Keywords: eduCommons OpenCourseWare course courses education educational open content
Platform: UNKNOWN
Classifier: Framework :: Plone
Classifier: Framework :: Zope2
Classifier: Framework :: Zope3
Classifier: Programming Language :: Python
Classifier: Topic :: Software Development :: Libraries :: Python Modules
